LICENSE
README.md
setup.py
renormalizer/__init__.py
renormalizer.egg-info/PKG-INFO
renormalizer.egg-info/SOURCES.txt
renormalizer.egg-info/dependency_links.txt
renormalizer.egg-info/requires.txt
renormalizer.egg-info/top_level.txt
renormalizer/cv/__init__.py
renormalizer/cv/finitet.py
renormalizer/cv/spectra_cv.py
renormalizer/cv/zerot.py
renormalizer/cv/tests/__init__.py
renormalizer/cv/tests/test_H_chain.py
renormalizer/cv/tests/test_abs.py
renormalizer/cv/tests/test_emi.py
renormalizer/lib/__init__.py
renormalizer/lib/bipartite_matching/__init__.py
renormalizer/lib/bipartite_matching/bipartite_matching.py
renormalizer/lib/davidson/__init__.py
renormalizer/lib/davidson/davidson.py
renormalizer/lib/davidson/logger.py
renormalizer/lib/integrate/__init__.py
renormalizer/lib/integrate/integrate.py
renormalizer/lib/integrate/_ivp/__init__.py
renormalizer/lib/integrate/_ivp/base.py
renormalizer/lib/integrate/_ivp/common.py
renormalizer/lib/integrate/_ivp/ivp.py
renormalizer/lib/integrate/_ivp/rk.py
renormalizer/lib/krylov/__init__.py
renormalizer/lib/krylov/krylov.py
renormalizer/model/__init__.py
renormalizer/model/basis.py
renormalizer/model/h_qc.py
renormalizer/model/model.py
renormalizer/model/mol.py
renormalizer/model/op.py
renormalizer/model/phonon.py
renormalizer/mps/__init__.py
renormalizer/mps/backend.py
renormalizer/mps/gs.py
renormalizer/mps/hop_expr.py
renormalizer/mps/lib.py
renormalizer/mps/matrix.py
renormalizer/mps/mp.py
renormalizer/mps/mpdm.py
renormalizer/mps/mpo.py
renormalizer/mps/mps.py
renormalizer/mps/svd_qn.py
renormalizer/mps/symbolic_mpo.py
renormalizer/mps/tda.py
renormalizer/mps/thermalprop.py
renormalizer/mps/tests/__init__.py
renormalizer/mps/tests/test_backend.py
renormalizer/mps/tests/test_elementop.py
renormalizer/mps/tests/test_evolve.py
renormalizer/mps/tests/test_gs.py
renormalizer/mps/tests/test_mp.py
renormalizer/mps/tests/test_mpdm.py
renormalizer/mps/tests/test_mpo.py
renormalizer/mps/tests/test_mpproperty.py
renormalizer/mps/tests/test_mps.py
renormalizer/mps/tests/test_sbm.py
renormalizer/mps/tests/test_tda.py
renormalizer/property/__init__.py
renormalizer/property/ops.py
