Metadata-Version: 2.1
Name: renormalizer
Version: 0.0.11
Home-page: https://github.com/shuaigroup/Renormalizer
License: Apache
Requires-Python: >=3.6
License-File: LICENSE
